rebasin/__init__.py
rebasin/loss/__init__.py
rebasin/loss/loss.py
rebasin/rebasinnet/__init__.py
rebasin/rebasinnet/sinkhorn.py
rebasin/rebasinnet/symmnet.py
rebasin/rebasinnet/graph/__init__.py
rebasin/rebasinnet/graph/auto_graph.py
rebasin/rebasinnet/graph/graph.py
sinkhorn_rebasin-0.0.2.dist-info/LICENSE
sinkhorn_rebasin-0.0.2.dist-info/METADATA
sinkhorn_rebasin-0.0.2.dist-info/WHEEL
sinkhorn_rebasin-0.0.2.dist-info/top_level.txt
sinkhorn_rebasin-0.0.2.dist-info/RECORD
