Metadata-Version: 2.1
Name: sinkhorn-rebasin
Version: 0.0.2
Summary: Python package for differentiable re-basin
Author: Fidel Guerrero Pena
Author-email: fidel-alejandro.guerrero-pena@etsmtl.ca
Classifier: Programming Language :: Python :: 3
Classifier: License :: OSI Approved :: MIT License
Classifier: Operating System :: POSIX :: Linux
Requires-Python: >=3.9
License-File: LICENSE
Requires-Dist: numpy
Requires-Dist: scipy
Requires-Dist: torch (>=1.11.0)
Requires-Dist: torchvision (>=0.12.0)
Requires-Dist: matplotlib
Requires-Dist: tqdm
Requires-Dist: torchviz
